{
  "applications": [
    {
      "id": 1
    },
    {
      "id": 2,
      "personalDetails": {
        "firstName": "aaaa",
        "lastName": "wwww",
        "dob": "1956-02-03",
        "phone": "345345345",
        "email": "xxxa@gmail.com"
      },
      "previousAddress": {
        "flatNumber": "mangoes-111",
        "address-1": "2214 Durand Road",
        "city": "Fortmill",
        "state": "SC",
        "country": "United States",
        "zipCode": "29715"
      },
      "currentAddress": {
        "flatNumber": "222",
        "address1": "222 sprint rd",
        "city": "Sprint city",
        "state": "NC",
        "country": "USA",
        "zipCode": "22222",
        "movingDate": "2018-02-02"
      }
    },
    {
      "id": 3,
      "personalDetails": {
        "firstName": "Venkateshwarlu",
        "lastName": "Yagatilee",
        "phone": "8036292367",
        "email": "venkyafhs@gmail.com",
        "dob": "1994-02-03"
      },
      "previousAddress": {
        "flatNumber": "207",
        "address-1": "902 Pine Springs Rd",
        "city": "Columbia",
        "state": "SC",
        "country": "United States",
        "zipCode": "29210"
      },
      "currentAddress": {
        "flatNumber": "207",
        "address1": "902 Pine Springs Rd",
        "city": "Columbia",
        "state": "SC",
        "country": "United States",
        "zipCode": "29210",
        "moveInDate": "2020-01-02"
      }
    }
  ]
}